wildfire_analyser/__init__.py
wildfire_analyser/cli.py
wildfire_analyser/gee_task_monitor.py
wildfire_analyser/fire_assessment/__init__.py
wildfire_analyser/fire_assessment/auth.py
wildfire_analyser/fire_assessment/deliverable_dependencies.py
wildfire_analyser/fire_assessment/deliverables.py
wildfire_analyser/fire_assessment/dependencies.py
wildfire_analyser/fire_assessment/dependency_graph.py
wildfire_analyser/fire_assessment/dependency_resolver.py
wildfire_analyser/fire_assessment/post_fire_assessment.py
wildfire_analyser/fire_assessment/products.py
wildfire_analyser/fire_assessment/resolver.py
wildfire_analyser/fire_assessment/sentinel2.py
wildfire_analyser/fire_assessment/time_windows.py
wildfire_analyser/fire_assessment/exporters/__init__.py
wildfire_analyser/fire_assessment/exporters/gcs.py
wildfire_analyser/fire_assessment/visualization/__init__.py
wildfire_analyser/fire_assessment/visualization/dnbr.py
wildfire_analyser/fire_assessment/visualization/dndvi.py
wildfire_analyser/fire_assessment/visualization/rbr.py
wildfire_analyser/fire_assessment/visualization/rgb.py
wildfire_analyser/fire_assessment/visualization/thumbnails.py
wildfire_analyser-0.2.15.dist-info/licenses/LICENSE
wildfire_analyser-0.2.15.dist-info/METADATA
wildfire_analyser-0.2.15.dist-info/WHEEL
wildfire_analyser-0.2.15.dist-info/top_level.txt
wildfire_analyser-0.2.15.dist-info/RECORD
