Metadata-Version: 2.4
Name: wildfire-analyser
Version: 0.2.15
Summary: Python library for post-fire assessment and wildfire analysis using Google Earth Engine.
Author: Marcelo Camargo
License-Expression: MIT
Project-URL: Homepage, https://github.com/camargo-advanced/wildfire-analyser
Project-URL: Source, https://github.com/camargo-advanced/wildfire-analyser
Project-URL: Issues, https://github.com/camargo-advanced/wildfire-analyser/issues
Requires-Python: >=3.10
License-File: LICENSE
Requires-Dist: geemap==0.36.6
Requires-Dist: geopandas==1.1.1
Requires-Dist: geedim==2.0.0
Requires-Dist: python-dotenv==1.0.1
Dynamic: license-file
